yiwen_package/__init__.py
yiwen_package/file_utils.py
yiwen_package/hello.py
yiwen_package/list_utils.py
yiwen_package/string_utils.py
yiwen_package/time_utils.py
yiwen_package-0.1.1.dist-info/METADATA
yiwen_package-0.1.1.dist-info/WHEEL
yiwen_package-0.1.1.dist-info/licenses/LICENSE
yiwen_package-0.1.1.dist-info/RECORD
