Metadata-Version: 2.4
Name: yiwen-package
Version: 0.1.1
Summary: 一个简单实用的 Python 工具包
License: MIT
License-File: LICENSE
Keywords: utils,utilities,tools,string,list,file,time
Author: yw.hao
Author-email: yiwenlemo@gmail.com
Requires-Python: >=3.9
Classifier: Development Status :: 3 - Alpha
Classifier: Intended Audience :: Developers
Classifier: License :: OSI Approved :: MIT License
Classifier: Programming Language :: Python :: 3
Classifier: Programming Language :: Python :: 3.9
Classifier: Programming Language :: Python :: 3.10
Classifier: Programming Language :: Python :: 3.11
Classifier: Programming Language :: Python :: 3.12
Classifier: Programming Language :: Python :: 3.13
Project-URL: Homepage, https://github.com/Hao-yiwen/yiwen-package
Project-URL: Issues, https://github.com/Hao-yiwen/yiwen-package/issues
Project-URL: Repository, https://github.com/Hao-yiwen/yiwen-package
